MANIFEST.in
README.rst
buildout.cfg
requirements.txt
setup.py
version.txt
bob/__init__.py
bob.hobpad2.veins.egg-info/PKG-INFO
bob.hobpad2.veins.egg-info/SOURCES.txt
bob.hobpad2.veins.egg-info/dependency_links.txt
bob.hobpad2.veins.egg-info/entry_points.txt
bob.hobpad2.veins.egg-info/requires.txt
bob.hobpad2.veins.egg-info/top_level.txt
bob/hobpad2/__init__.py
bob/hobpad2/veins/__init__.py
bob/hobpad2/veins/script.py
bob/hobpad2/veins/configurations/__init__.py
bob/hobpad2/veins/configurations/mc_bio.py
bob/hobpad2/veins/configurations/mc_pa.py
bob/hobpad2/veins/configurations/rlt_bio.py
bob/hobpad2/veins/configurations/rlt_pa.py
bob/hobpad2/veins/configurations/wld_bio.py
bob/hobpad2/veins/configurations/wld_pa.py
bob/hobpad2/veins/scores/mc/B-va/nonorm/scores-dev
bob/hobpad2/veins/scores/mc/B/nonorm/scores-dev
bob/hobpad2/veins/scores/mc/Fifty-va/nonorm/scores-dev
bob/hobpad2/veins/scores/mc/Fifty/nonorm/scores-dev
bob/hobpad2/veins/scores/mc/Full-va/nonorm/scores-dev
bob/hobpad2/veins/scores/mc/Full/nonorm/scores-dev
bob/hobpad2/veins/scores/mc/Nom-va/nonorm/scores-dev
bob/hobpad2/veins/scores/mc/Nom/nonorm/scores-dev
bob/hobpad2/veins/scores/pad-competition/blab/cropped/scores-dev
bob/hobpad2/veins/scores/pad-competition/blab/cropped/scores-dev.orig
bob/hobpad2/veins/scores/pad-competition/blab/cropped/scores-eval
bob/hobpad2/veins/scores/pad-competition/blab/cropped/scores-eval-encoded.orig
bob/hobpad2/veins/scores/pad-competition/blab/cropped/scores-eval.orig
bob/hobpad2/veins/scores/pad-competition/blab/full/scores-dev
bob/hobpad2/veins/scores/pad-competition/blab/full/scores-dev.orig
bob/hobpad2/veins/scores/pad-competition/blab/full/scores-eval
bob/hobpad2/veins/scores/pad-competition/blab/full/scores-eval-encoded.orig
bob/hobpad2/veins/scores/pad-competition/blab/full/scores-eval.orig
bob/hobpad2/veins/scores/pad-competition/grip-priamus/cropped/scores-dev
bob/hobpad2/veins/scores/pad-competition/grip-priamus/cropped/scores-dev.orig
bob/hobpad2/veins/scores/pad-competition/grip-priamus/cropped/scores-eval
bob/hobpad2/veins/scores/pad-competition/grip-priamus/cropped/scores-eval-encoded.orig
bob/hobpad2/veins/scores/pad-competition/grip-priamus/cropped/scores-eval.orig
