Metadata-Version: 1.1
Name: bob.hobpad2.veins
Version: 1.0.2
Summary: Software package to reproduce experiments of Chapter 18, "An Introduction to Vein Presentation Attacks and Detection" of the "Handbook of Biometric Anti-Spoofing: Presentation Attack Detection 2nd Edition" book
Home-page: https://gitlab.idiap.ch/bob/bob.hobpad2.veins
Author: Andre Anjos
Author-email: andre.anjos@idiap.ch
License: GPLv3
Keywords: bob
Platform: UNKNOWN
Classifier: Framework :: Bob
Classifier: Development Status :: 4 - Beta
Classifier: Intended Audience :: Developers
Classifier: License :: OSI Approved :: GNU General Public License v3 (GPLv3)
Classifier: Natural Language :: English
Classifier: Programming Language :: Python
Classifier: Programming Language :: Python :: 3
Classifier: Topic :: Scientific/Engineering :: Artificial Intelligence
Classifier: Topic :: Software Development :: Libraries :: Python Modules
